nonebot_plugin_picstatus_template_zhenxun/__init__.py
nonebot_plugin_picstatus_template_zhenxun/__main__.py
nonebot_plugin_picstatus_template_zhenxun/config.py
nonebot_plugin_picstatus_template_zhenxun/res/bk.png
nonebot_plugin_picstatus_template_zhenxun/res/index.css
nonebot_plugin_picstatus_template_zhenxun/res/index.html.jinja
nonebot_plugin_picstatus_template_zhenxun/res/top.jpg
nonebot_plugin_picstatus_template_zhenxun-0.2.0.dist-info/METADATA
nonebot_plugin_picstatus_template_zhenxun-0.2.0.dist-info/WHEEL
nonebot_plugin_picstatus_template_zhenxun-0.2.0.dist-info/licenses/LICENSE
nonebot_plugin_picstatus_template_zhenxun-0.2.0.dist-info/RECORD
