Metadata-Version: 2.4
Name: nonebot-plugin-picstatus-template-zhenxun
Version: 0.2.0
Summary: Template plugin project
Project-URL: homepage, https://github.com/lgc-NB2Dev/nonebot-plugin-picstatus-template-zhenxun
Author-email: LgCookie <lgc2333@126.com>
License: AGPL-3.0-or-later
License-File: LICENSE
Requires-Python: <4.0,>=3.10
Requires-Dist: cookit[jinja,playwright,pydantic]>=0.13.1
Requires-Dist: nonebot-plugin-htmlrender>=0.6.6
Requires-Dist: nonebot-plugin-picstatus>=2.2.0
Requires-Dist: nonebot2>=2.4.3
